saas_to_mcp/__init__.py
saas_to_mcp/cli.py
saas_to_mcp/models.py
saas_to_mcp/server.py
saas_to_mcp-0.2.0.dist-info/METADATA
saas_to_mcp-0.2.0.dist-info/WHEEL
saas_to_mcp-0.2.0.dist-info/entry_points.txt
saas_to_mcp-0.2.0.dist-info/licenses/LICENSE
saas_to_mcp-0.2.0.dist-info/RECORD
